LICENSE.txt
README.md
taskflow_sdk/__init__.py
taskflow_sdk/__main__.py
taskflow_sdk/cli/__init__.py
taskflow_sdk/cli/arguments.py
taskflow_sdk/constants.py
taskflow_sdk/endpoint.py
taskflow_sdk/events.py
taskflow_sdk/exceptions.py
taskflow_sdk/executor.py
taskflow_sdk/forms.py
taskflow_sdk/grpc_errors.py
taskflow_sdk/grpc_py/__init__.py
taskflow_sdk/grpc_py/action_webhook_pb2.py
taskflow_sdk/grpc_py/action_webhook_pb2.pyi
taskflow_sdk/grpc_py/action_webhook_pb2_grpc.py
taskflow_sdk/grpc_server.py
taskflow_sdk/interfaces.py
taskflow_sdk/knowledge_base/__init__.py
taskflow_sdk/knowledge_base/actions.py
taskflow_sdk/knowledge_base/storage.py
taskflow_sdk/knowledge_base/utils.py
taskflow_sdk/plugin.py
taskflow_sdk/slots.py
taskflow_sdk/tracing/config.py
taskflow_sdk/tracing/endpoints.py
taskflow_sdk/tracing/instrumentation/attribute_extractors.py
taskflow_sdk/tracing/instrumentation/instrumentation.py
taskflow_sdk/tracing/tracer_register.py
taskflow_sdk/tracing/utils.py
taskflow_sdk/types.py
taskflow_sdk/utils.py
taskflow_sdk/version.py
taskflow_sdk-3.10.1.dist-info/LICENSE.txt
taskflow_sdk-3.10.1.dist-info/METADATA
taskflow_sdk-3.10.1.dist-info/WHEEL
taskflow_sdk-3.10.1.dist-info/RECORD
