Metadata-Version: 2.1
Name: taskflow-sdk
Version: 3.10.1
Summary: Open source machine learning framework to automate text- and voice-based conversations: NLU, dialogue management, connect to Slack, Facebook, and more - Create chatbots and voice assistants
Home-page: https://taskflow.com
License: Apache-2.0
Keywords: nlp,machine-learning,machine-learning-library,bot,bots,botkit,taskflow conversational-agents,conversational-ai,chatbot,chatbot-framework,bot-framework
Author: Taskflow Technologies GmbH
Author-email: hi@taskflow.com
Maintainer: Tom Bocklisch
Maintainer-email: tom@taskflow.com
Requires-Python: >=3.8,<3.11
Classifier: Development Status :: 5 - Production/Stable
Classifier: Intended Audience :: Developers
Classifier: License :: OSI Approved :: Apache Software License
Classifier: Programming Language :: Python :: 3
Classifier: Programming Language :: Python :: 3.8
Classifier: Programming Language :: Python :: 3.9
Classifier: Programming Language :: Python :: 3.10
Classifier: Topic :: Software Development :: Libraries
Requires-Dist: Sanic-Cors (>=2.0.0,<3.0.0)
Requires-Dist: coloredlogs (>=10,<16)
Requires-Dist: grpcio (==1.59.3)
Requires-Dist: grpcio-health-checking (==1.59.3)
Requires-Dist: grpcio-tools (==1.56.2)
Requires-Dist: opentelemetry-api (>=1.16.0,<1.17.0)
Requires-Dist: opentelemetry-exporter-jaeger (>=1.16.0,<1.17.0)
Requires-Dist: opentelemetry-exporter-otlp (>=1.16.0,<1.17.0)
Requires-Dist: opentelemetry-sdk (>=1.16.0,<1.17.0)
Requires-Dist: pluggy (>=1.0.0,<2.0.0)
Requires-Dist: prompt-toolkit (>=3.0,<3.0.29)
Requires-Dist: protobuf (==4.25.3)
Requires-Dist: pydantic (>=2.6.4,<3.0.0)
Requires-Dist: ruamel.yaml (>=0.16.5,<0.18.0)
Requires-Dist: sanic (>=22.12,<23.0)
Requires-Dist: typing-extensions (>=4.1.1,<5.0.0)
Requires-Dist: websockets (>=10.0,<12.0)
Project-URL: Documentation, https://taskflow.com/docs
Project-URL: Repository, https://github.com/taskflowhq/taskflow-sdk
